<data><Converstion><Date>2021/12/21_09:15:00</Date><Information>Melting Point of Ice</Information><InformationEnter/><InformationGiven> °C: 0 °F: 32  K: 273.15</InformationGiven></Converstion><Converstion><Date>2021/12/21_09:15:02</Date><Information>Absolute Zero</Information><InformationEnter/><InformationGiven> °C: -273.15 °F: -459.67  K: 0</InformationGiven></Converstion><Converstion><Date>2021/12/21_09:15:04</Date><Information>Room Temperature</Information><InformationEnter/><InformationGiven> °C: 22 °F: 71.6  K: 295.15</InformationGiven></Converstion><Converstion><Date>2021/12/21_09:15:06</Date><Information>Body Temperature</Information><InformationEnter/><InformationGiven> °C: 37 °F: 71.6  K: 295.15</InformationGiven></Converstion><Converstion><Date>2021/12/21_09:15:09</Date><Information>User Temperature</Information><InformationEnter> °C: 9</InformationEnter><InformationGiven>  K: 282.15 °F: 48.2</InformationGiven></Converstion><Converstion><Date>2021/12/21_09:15:12</Date><Information>User Temperature</Information><InformationEnter> °F: 886</InformationEnter><InformationGiven> °C: 474.4824  K: 747.5944444444444</InformationGiven></Converstion><Converstion><Date>2021/12/21_09:15:15</Date><Information>User Temperature</Information><InformationEnter> °F: 10115.33</InformationEnter><InformationGiven> °C: 5601.85  K: 5875</InformationGiven></Converstion><Converstion><Date>2021/12/21_09:15:19</Date><Information>Boiling Point of Water</Information><InformationEnter/><InformationGiven> °C: 100 °F: 212  K: 373.15</InformationGiven></Converstion><Converstion><Date>2021/12/21_09:18:28</Date><Information>User Temperature</Information><InformationEnter> °C: 56427625561465446</InformationEnter><InformationGiven>  K: 5.642762556146572E16 °F: 1.0156972601063784E17</InformationGiven></Converstion><Converstion><Date>2021/12/21_09:18:35</Date><Information>User Temperature</Information><InformationEnter/><InformationGiven> °C: 56427625561465446 °F: 1.0156972601063784E17  K: 5.642762556146572E16</InformationGiven></Converstion><Converstion><Date>2021/12/21_09:18:49</Date><Information>User Temperature</Information><InformationEnter> °F: 9</InformationEnter><InformationGiven> °C: -12.7788  K: 260.3722222222222</InformationGiven></Converstion></data>